{
  "project_info": {
    "project_number": "726913518422",
    "firebase_url": "https://unity-test-97af2.firebaseio.com",
    "project_id": "unity-test-97af2",
    "storage_bucket": "unity-test-97af2.appspot.com"
  },
  "client": [
    {
      "client_info": {
        "mobilesdk_app_id": "1:726913518422:android:0d7bb63f25524bfc",
        "android_client_info": {
          "package_name": "com.kirov.prototypeapp"
        }
      },
      "oauth_client": [
        {
          "client_id": "726913518422-ig4cinctdbbp294l3pljgronnaha42jp.apps.googleusercontent.com",
          "client_type": 3
        }
      ],
      "api_key": [
        {
          "current_key": "AIzaSyD7oQ0SQVDeRNrWbbNkp2pJYzgAIISXkVc"
        }
      ],
      "services": {
        "analytics_service": {
          "status": 1
        },
        "appinvite_service": {
          "status": 1,
          "other_platform_oauth_client": []
        },
        "ads_service": {
          "status": 2
        }
      }
    }
  ],
  "configuration_version": "1"
}